CHANGELOG.txt
LICENSE.txt
MANIFEST.in
README.txt
ez_setup.py
setup.cfg
setup.py
AuthTkt.egg-info/PKG-INFO
AuthTkt.egg-info/SOURCES.txt
AuthTkt.egg-info/dependency_links.txt
AuthTkt.egg-info/entry_points.txt
AuthTkt.egg-info/not-zip-safe
AuthTkt.egg-info/requires.txt
AuthTkt.egg-info/top_level.txt
authtkt/__init__.py
authtkt/service.py
authtkt/app/__init__.py
authtkt/app/index.py
doc/Makefile
doc/index.txt
doc/source/api.rst
doc/source/conf.py
doc/source/index.rst
doc/source/manual.rst
test/README.txt
test/doc.py