Metadata-Version: 1.0
Name: AuthTkt
Version: 0.3.3
Summary: Python implementation of the mod_auth_tkt handler and Perl scripts
Home-page: UNKNOWN
Author: James Gardner
Author-email: UNKNOWN
License: Apache 2.0
Platform: UNKNOWN
Classifier: Development Status :: 3 - Alpha
Classifier: License :: OSI Approved :: Apache Software License
Classifier: Programming Language :: Python :: 2
Classifier: Topic :: Software Development :: Libraries :: Python Modules
Classifier: Topic :: System :: Systems Administration :: Authentication/Directory
Classifier: Environment :: Web Environment
